smart_imports/__init__.py
smart_imports/ast_parser.py
smart_imports/cache.py
smart_imports/config.py
smart_imports/constants.py
smart_imports/discovering.py
smart_imports/exceptions.py
smart_imports/fixtures/python_3_10_packages.txt
smart_imports/fixtures/python_3_5_packages.txt
smart_imports/fixtures/python_3_6_packages.txt
smart_imports/fixtures/python_3_7_packages.txt
smart_imports/fixtures/python_3_8_packages.txt
smart_imports/fixtures/python_3_9_packages.txt
smart_imports/helpers.py
smart_imports/importer.py
smart_imports/plugins/__init__.pt
smart_imports/plugins/__init__.py
smart_imports/plugins/mypy.py
smart_imports/rules.py
smart_imports/scopes_tree.py
smart_imports/tests/__init__.py
smart_imports/tests/fixtures/python_3_10/full_parser_test.py
smart_imports/tests/fixtures/python_3_5/full_parser_test.py
smart_imports/tests/fixtures/python_3_6/full_parser_test.py
smart_imports/tests/fixtures/python_3_7/full_parser_test.py
smart_imports/tests/fixtures/python_3_8/full_parser_test.py
smart_imports/tests/fixtures/python_3_9/full_parser_test.py
smart_imports/tests/test_ast_parser.py
smart_imports/tests/test_cache.py
smart_imports/tests/test_config.py
smart_imports/tests/test_discovering.py
smart_imports/tests/test_importer.py
smart_imports/tests/test_rules.py
smart_imports/tests/test_scopes_tree.py
smart_imports-0.2.7.dist-info/LICENSE
smart_imports-0.2.7.dist-info/WHEEL
smart_imports-0.2.7.dist-info/METADATA
smart_imports-0.2.7.dist-info/RECORD
